capstone_text_mining/__init__.py
capstone_text_mining/data_clean.py
capstone_text_mining/feature_importance.py
capstone_text_mining/graph_prep.py
capstone_text_mining/graph_viz.py
capstone_text_mining/hand_labelled_features.py
capstone_text_mining/lift.py
capstone_text_mining/model.py
capstone_text_mining/recode_categorical.py
capstone_text_mining/sent_analysis.py
capstone_text_mining/shap_visualization.py
capstone_text_mining/spacy_functions.py
capstone_text_mining/topic_model_features.py
capstone_text_mining-0.1.2.dist-info/LICENSE.txt
capstone_text_mining-0.1.2.dist-info/METADATA
capstone_text_mining-0.1.2.dist-info/WHEEL
capstone_text_mining-0.1.2.dist-info/top_level.txt
capstone_text_mining-0.1.2.dist-info/RECORD
