Metadata-Version: 2.1
Name: capstone-text-mining
Version: 0.1.2
Summary: Capstone Text Mining Techniques
Home-page: https://github.com/mfligiel/Capstone_Text_Mining
Author: Matt Fligiel, Carmin Ballou, Zain Jafri
Author-email: matthewfligiel@gmail.com
License: Apache License 2.0
Platform: UNKNOWN
Requires-Dist: numpy
Requires-Dist: pandas
Requires-Dist: matplotlib
Requires-Dist: seaborn
Requires-Dist: tqdm
Requires-Dist: sklearn
Requires-Dist: nltk
Requires-Dist: vaderSentiment
Requires-Dist: spacy
Requires-Dist: networkx
Requires-Dist: gensim
Requires-Dist: pyLDAvis (==2.1.2)
Requires-Dist: snorkel
